pyprc-1.0.0.dist-info/METADATA
pyprc-1.0.0.dist-info/WHEEL
pyprc/__init__.py
pyprc/pyprc.pyd
pyprc-1.0.0.dist-info/RECORD
