Metadata-Version: 2.4
Name: pyprc
Version: 1.0.0
Author: BenHall-7 <Benjaminjahall@gmail.com>
Author-email: BenHall-7 <Benjaminjahall@gmail.com>
